cliface/__init__.py
cliface/cliface.py
cliface/layout/__init__.py
cliface/layout/appframe.py
cliface/layout/components.py
cliface/layout/dynamic_window.py
cliface/layout/menu_options.py
cliface/screens/__init__.py
cliface/screens/confirmation_screen.py
cliface/screens/input_screen.py
cliface/screens/menu_screen.py
cliface/utils/__init__.py
cliface/utils/break_text.py
cliface/utils/clear_terminal.py
cliface/utils/theme_loader.py
cliface/utils/themes/dark.json
cliface/utils/themes/light.json
cliface-1.0.3.dist-info/METADATA
cliface-1.0.3.dist-info/WHEEL
cliface-1.0.3.dist-info/top_level.txt
cliface-1.0.3.dist-info/RECORD
