Metadata-Version: 2.4
Name: cliface
Version: 1.0.3
Summary: A CLI toolkit library.
Home-page: https://github.com/iamtwobe/cliface
Author: iamtwobe
Author-email: contato.iamtwobe@gmail.com
License: MIT
Classifier: License :: OSI Approved :: MIT License
Classifier: Programming Language :: Python :: 3
Classifier: Operating System :: OS Independent
Requires-Python: >=3.12
Requires-Dist: prompt_toolkit>=3.0.50
Requires-Dist: wcwidth>=0.2.13
Dynamic: author
Dynamic: author-email
Dynamic: classifier
Dynamic: description-content-type
Dynamic: home-page
Dynamic: license
Dynamic: requires-dist
Dynamic: requires-python
Dynamic: summary
